pywiim/__init__.py
pywiim/backoff.py
pywiim/capabilities.py
pywiim/client.py
pywiim/device_capabilities.py
pywiim/discovery.py
pywiim/exceptions.py
pywiim/group.py
pywiim/group_helpers.py
pywiim/metadata.py
pywiim/models.py
pywiim/normalize.py
pywiim/polling.py
pywiim/profiles.py
pywiim/py.typed
pywiim/role.py
pywiim/state.py
pywiim/api/__init__.py
pywiim/api/audio_pro.py
pywiim/api/audio_settings.py
pywiim/api/base.py
pywiim/api/bluetooth.py
pywiim/api/constants.py
pywiim/api/device.py
pywiim/api/diagnostics.py
pywiim/api/endpoints.py
pywiim/api/eq.py
pywiim/api/firmware.py
pywiim/api/group.py
pywiim/api/lms.py
pywiim/api/loop_mode.py
pywiim/api/misc.py
pywiim/api/parser.py
pywiim/api/playback.py
pywiim/api/preset.py
pywiim/api/ssl.py
pywiim/api/subwoofer.py
pywiim/api/timer.py
pywiim/cli/__init__.py
pywiim/cli/diagnostics.py
pywiim/cli/discovery_cli.py
pywiim/cli/group_test_cli.py
pywiim/cli/join_test_cli.py
pywiim/cli/monitor_cli.py
pywiim/cli/verify_cli.py
pywiim/player/__init__.py
pywiim/player/audio.py
pywiim/player/base.py
pywiim/player/bluetooth.py
pywiim/player/coverart.py
pywiim/player/debounce.py
pywiim/player/diagnostics.py
pywiim/player/groupops.py
pywiim/player/media.py
pywiim/player/playback.py
pywiim/player/properties.py
pywiim/player/source_capabilities.py
pywiim/player/statemgr.py
pywiim/player/stream.py
pywiim/player/stream_enricher.py
pywiim/player/volume.py
pywiim/upnp/__init__.py
pywiim/upnp/client.py
pywiim/upnp/eventer.py
pywiim/upnp/health.py
pywiim-2.1.71.dist-info/licenses/LICENSE
pywiim-2.1.71.dist-info/METADATA
pywiim-2.1.71.dist-info/WHEEL
pywiim-2.1.71.dist-info/entry_points.txt
pywiim-2.1.71.dist-info/top_level.txt
pywiim-2.1.71.dist-info/RECORD
