Metadata-Version: 2.4
Name: pywiim
Version: 2.1.71
Summary: Python library for WiiM/LinkPlay device communication
Author-email: Michael Cumming <mjcumming@gmail.com>
License: MIT
Project-URL: Homepage, https://github.com/mjcumming/pywiim
Project-URL: Repository, https://github.com/mjcumming/pywiim
Project-URL: Issues, https://github.com/mjcumming/pywiim/issues
Keywords: wiim,linkplay,audio,upnp,streaming,music,async
Classifier: Development Status :: 5 - Production/Stable
Classifier: Intended Audience :: Developers
Classifier: License :: OSI Approved :: MIT License
Classifier: Programming Language :: Python :: 3
Classifier: Programming Language :: Python :: 3.11
Classifier: Programming Language :: Python :: 3.12
Classifier: Topic :: Multimedia :: Sound/Audio
Classifier: Topic :: Software Development :: Libraries :: Python Modules
Classifier: Typing :: Typed
Requires-Python: >=3.11
License-File: LICENSE
Requires-Dist: aiohttp>=3.8.0
Requires-Dist: pydantic>=2.0.0
Requires-Dist: async-upnp-client>=0.40.0
Requires-Dist: m3u8>=3.5.0
Requires-Dist: mutagen>=1.47.0
Provides-Extra: dev
Requires-Dist: black>=23.0.0; extra == "dev"
Requires-Dist: isort>=5.12.0; extra == "dev"
Requires-Dist: ruff>=0.1.0; extra == "dev"
Requires-Dist: mypy>=1.0.0; extra == "dev"
Requires-Dist: pytest>=7.0.0; extra == "dev"
Requires-Dist: pytest-asyncio>=0.21.0; extra == "dev"
Requires-Dist: pytest-cov>=4.0.0; extra == "dev"
Requires-Dist: pytest-xdist>=3.0.0; extra == "dev"
Requires-Dist: pyyaml>=6.0.0; extra == "dev"
Dynamic: license-file
